tomy/__init__.py
tomy/salt.py
tomy/utils.py
tomy-0.0.4.dist-info/METADATA
tomy-0.0.4.dist-info/RECORD
tomy-0.0.4.dist-info/WHEEL
tomy-0.0.4.dist-info/top_level.txt
