Metadata-Version: 2.1
Name: tomy
Version: 0.0.4
Summary: Bunch of useful python codes
Home-page: https://github.com/Tomvictor/tomy
Author: Tom Victor
Author-email: vjtomvictor@gmail.com
License: UNKNOWN
Platform: UNKNOWN
Classifier: Programming Language :: Python :: 3
Classifier: License :: OSI Approved :: MIT License
Classifier: Operating System :: OS Independent
